FADS/__init__.py
FADS/sampling_fns.py
FADS-1.0.1.dist-info/LICENSE
FADS-1.0.1.dist-info/METADATA
FADS-1.0.1.dist-info/WHEEL
FADS-1.0.1.dist-info/top_level.txt
FADS-1.0.1.dist-info/RECORD
