Metadata-Version: 2.1
Name: FADS
Version: 1.0.1
Summary: Fast Diversity Subsampling from a Data Set
Home-page: https://github.com/boyangshang/FADS
Author: Boyang Shang, Daniel Apley, Sanjay Mehrotra
Author-email: boyangshang2015@u.northwestern.edu
License: MIT
Classifier: License :: OSI Approved :: MIT License
Classifier: Programming Language :: Python :: 3
Classifier: Programming Language :: Python :: 3.7
License-File: LICENSE
Requires-Dist: numpy
Requires-Dist: scikit-learn
